{
  "1": {
    "status": "no_image",
    "faces": []
  },
  "2": {
    "status": "no_image",
    "faces": []
  },
  "3": {
    "status": "no_image",
    "faces": []
  },
  "4": {
    "status": "no_image",
    "faces": []
  },
  "5": {
    "status": "no_image",
    "faces": []
  },
  "6": {
    "status": "no_image",
    "faces": []
  },
  "7": {
    "status": "no_image",
    "faces": []
  },
  "8": {
    "status": "ok",
    "faces": [
      {
        "person": "Sia",
        "rolle": "Baby",
        "confidence": 50.2
      },
      {
        "person": "Lias",
        "rolle": "Jüngerer Sohn von Melly & Johannes, Cousin von Sia",
        "confidence": 60.9
      }
    ],
    "count": 2,
    "names": [
      "Sia",
      "Lias"
    ]
  },
  "9": {
    "status": "ok",
    "faces": [
      {
        "person": "Sia",
        "rolle": "Baby",
        "confidence": 67.7
      }
    ],
    "count": 1,
    "names": [
      "Sia"
    ]
  },
  "10": {
    "status": "ok",
    "faces": [
      {
        "person": "Sia",
        "rolle": "Baby",
        "confidence": 46.8
      }
    ],
    "count": 1,
    "names": [
      "Sia"
    ]
  },
  "11": {
    "status": "ok",
    "faces": [
      {
        "person": "Leano",
        "rolle": "Sohn von Vanessa & Mark, Cousin von Sia",
        "confidence": 65.3
      },
      {
        "person": "Sia",
        "rolle": "Baby",
        "confidence": 85.4
      }
    ],
    "count": 2,
    "names": [
      "Leano",
      "Sia"
    ]
  },
  "12": {
    "status": "ok",
    "faces": [
      {
        "person": "Lias",
        "rolle": "Jüngerer Sohn von Melly & Johannes, Cousin von Sia",
        "confidence": 66.9
      },
      {
        "person": "Sia",
        "rolle": "Baby",
        "confidence": 51.4
      }
    ],
    "count": 2,
    "names": [
      "Lias",
      "Sia"
    ]
  },
  "13": {
    "status": "ok",
    "faces": [
      {
        "person": "Mama",
        "rolle": "Mama",
        "confidence": 81.4
      },
      {
        "person": "Sia",
        "rolle": "Baby",
        "confidence": 40.4
      }
    ],
    "count": 2,
    "names": [
      "Mama",
      "Sia"
    ]
  },
  "14": {
    "status": "ok",
    "faces": [
      {
        "person": "Sia",
        "rolle": "Baby",
        "confidence": 32.9
      },
      {
        "person": "Sia",
        "rolle": "Baby",
        "confidence": 45.2
      }
    ],
    "count": 2,
    "names": [
      "Sia",
      "Sia"
    ]
  },
  "15": {
    "status": "ok",
    "faces": [
      {
        "person": "Sia",
        "rolle": "Baby",
        "confidence": 28.9
      },
      {
        "person": "Sia",
        "rolle": "Baby",
        "confidence": 38.5
      },
      {
        "person": "Sia",
        "rolle": "Baby",
        "confidence": 34.5
      }
    ],
    "count": 3,
    "names": [
      "Sia",
      "Sia",
      "Sia"
    ]
  },
  "16": {
    "status": "ok",
    "faces": [
      {
        "person": "Lias",
        "rolle": "Jüngerer Sohn von Melly & Johannes, Cousin von Sia",
        "confidence": 66.4
      }
    ],
    "count": 1,
    "names": [
      "Lias"
    ]
  },
  "17": {
    "status": "ok",
    "faces": [
      {
        "person": "Vanessa",
        "rolle": "Schwester von Christian, Mama von Leano",
        "confidence": 73.6
      },
      {
        "person": "Lias",
        "rolle": "Jüngerer Sohn von Melly & Johannes, Cousin von Sia",
        "confidence": 57.3
      }
    ],
    "count": 2,
    "names": [
      "Vanessa",
      "Lias"
    ]
  },
  "18": {
    "status": "ok",
    "faces": [
      {
        "person": "Sia",
        "rolle": "Baby",
        "confidence": 53.3
      },
      {
        "person": "Sia",
        "rolle": "Baby",
        "confidence": 33.8
      }
    ],
    "count": 2,
    "names": [
      "Sia",
      "Sia"
    ]
  },
  "19": {
    "status": "ok",
    "faces": [
      {
        "person": "Sia",
        "rolle": "Baby",
        "confidence": 40.9
      }
    ],
    "count": 1,
    "names": [
      "Sia"
    ]
  },
  "20": {
    "status": "ok",
    "faces": [
      {
        "person": "Mama",
        "rolle": "Mama",
        "confidence": 81.8
      },
      {
        "person": "Papa",
        "rolle": "Papa",
        "confidence": 78.1
      },
      {
        "person": "Sia",
        "rolle": "Baby",
        "confidence": 64.5
      }
    ],
    "count": 3,
    "names": [
      "Mama",
      "Papa",
      "Sia"
    ]
  },
  "21": {
    "status": "ok",
    "faces": [
      {
        "person": "Leano",
        "rolle": "Sohn von Vanessa & Mark, Cousin von Sia",
        "confidence": 75.7
      },
      {
        "person": "Sia",
        "rolle": "Baby",
        "confidence": 75.6
      },
      {
        "person": "Levi",
        "rolle": "Ältester Sohn von Melly & Johannes, Cousin von Sia",
        "confidence": 67.4
      }
    ],
    "count": 3,
    "names": [
      "Leano",
      "Sia",
      "Levi"
    ]
  },
  "22": {
    "status": "ok",
    "faces": [
      {
        "person": "Sia",
        "rolle": "Baby",
        "confidence": 100.0
      }
    ],
    "count": 1,
    "names": [
      "Sia"
    ]
  },
  "23": {
    "status": "ok",
    "faces": [
      {
        "person": "Sia",
        "rolle": "Baby",
        "confidence": 71.7
      }
    ],
    "count": 1,
    "names": [
      "Sia"
    ]
  },
  "24": {
    "status": "ok",
    "faces": [
      {
        "person": "Sia",
        "rolle": "Baby",
        "confidence": 74.4
      },
      {
        "person": "Timo",
        "rolle": "Cousin & Patenonkel",
        "confidence": 64.2
      }
    ],
    "count": 2,
    "names": [
      "Sia",
      "Timo"
    ]
  },
  "25": {
    "status": "ok",
    "faces": [
      {
        "person": "Papa",
        "rolle": "Papa",
        "confidence": 57.9
      },
      {
        "person": "Sia",
        "rolle": "Baby",
        "confidence": 35.6
      }
    ],
    "count": 2,
    "names": [
      "Papa",
      "Sia"
    ]
  },
  "26": {
    "status": "ok",
    "faces": [
      {
        "person": "Sia",
        "rolle": "Baby",
        "confidence": 34.8
      }
    ],
    "count": 1,
    "names": [
      "Sia"
    ]
  },
  "27": {
    "status": "ok",
    "faces": [
      {
        "person": "Sia",
        "rolle": "Baby",
        "confidence": 39.2
      }
    ],
    "count": 1,
    "names": [
      "Sia"
    ]
  },
  "28": {
    "status": "ok",
    "faces": [
      {
        "person": "Sia",
        "rolle": "Baby",
        "confidence": 45.2
      }
    ],
    "count": 1,
    "names": [
      "Sia"
    ]
  },
  "29": {
    "status": "ok",
    "faces": [
      {
        "person": "Sia",
        "rolle": "Baby",
        "confidence": 37.3
      },
      {
        "person": "Sia",
        "rolle": "Baby",
        "confidence": 45.8
      }
    ],
    "count": 2,
    "names": [
      "Sia",
      "Sia"
    ]
  },
  "30": {
    "status": "ok",
    "faces": [
      {
        "person": "Sia",
        "rolle": "Baby",
        "confidence": 43.6
      }
    ],
    "count": 1,
    "names": [
      "Sia"
    ]
  },
  "31": {
    "status": "ok",
    "faces": [
      {
        "person": "Sia",
        "rolle": "Baby",
        "confidence": 52.2
      }
    ],
    "count": 1,
    "names": [
      "Sia"
    ]
  },
  "32": {
    "status": "ok",
    "faces": [
      {
        "person": "Lias",
        "rolle": "Jüngerer Sohn von Melly & Johannes, Cousin von Sia",
        "confidence": 66.4
      }
    ],
    "count": 1,
    "names": [
      "Lias"
    ]
  },
  "33": {
    "status": "ok",
    "faces": [
      {
        "person": "Mama",
        "rolle": "Mama",
        "confidence": 75.2
      },
      {
        "person": "Sia",
        "rolle": "Baby",
        "confidence": 41.7
      }
    ],
    "count": 2,
    "names": [
      "Mama",
      "Sia"
    ]
  },
  "34": {
    "status": "ok",
    "faces": [
      {
        "person": "Sia",
        "rolle": "Baby",
        "confidence": 44.0
      }
    ],
    "count": 1,
    "names": [
      "Sia"
    ]
  },
  "35": {
    "status": "ok",
    "faces": [
      {
        "person": "Sia",
        "rolle": "Baby",
        "confidence": 42.3
      }
    ],
    "count": 1,
    "names": [
      "Sia"
    ]
  },
  "36": {
    "status": "ok",
    "faces": [
      {
        "person": "Sia",
        "rolle": "Baby",
        "confidence": 36.7
      }
    ],
    "count": 1,
    "names": [
      "Sia"
    ]
  },
  "37": {
    "status": "ok",
    "faces": [
      {
        "person": "Sia",
        "rolle": "Baby",
        "confidence": 53.3
      },
      {
        "person": "Sia",
        "rolle": "Baby",
        "confidence": 33.8
      }
    ],
    "count": 2,
    "names": [
      "Sia",
      "Sia"
    ]
  },
  "38": {
    "status": "ok",
    "faces": [
      {
        "person": "Sia",
        "rolle": "Baby",
        "confidence": 39.3
      }
    ],
    "count": 1,
    "names": [
      "Sia"
    ]
  },
  "39": {
    "status": "ok",
    "faces": [
      {
        "person": "Sia",
        "rolle": "Baby",
        "confidence": 33.2
      },
      {
        "person": "Sia",
        "rolle": "Baby",
        "confidence": 37.5
      }
    ],
    "count": 2,
    "names": [
      "Sia",
      "Sia"
    ]
  },
  "40": {
    "status": "ok",
    "faces": [
      {
        "person": "Sia",
        "rolle": "Baby",
        "confidence": 26.5
      },
      {
        "person": "Sia",
        "rolle": "Baby",
        "confidence": 27.4
      }
    ],
    "count": 2,
    "names": [
      "Sia",
      "Sia"
    ]
  },
  "41": {
    "status": "ok",
    "faces": [
      {
        "person": "Sia",
        "rolle": "Baby",
        "confidence": 43.5
      },
      {
        "person": "Papa",
        "rolle": "Papa",
        "confidence": 78.3
      }
    ],
    "count": 2,
    "names": [
      "Sia",
      "Papa"
    ]
  },
  "42": {
    "status": "ok",
    "faces": [
      {
        "person": "Sia",
        "rolle": "Baby",
        "confidence": 38.4
      },
      {
        "person": "Sia",
        "rolle": "Baby",
        "confidence": 35.0
      },
      {
        "person": "Sia",
        "rolle": "Baby",
        "confidence": 33.7
      }
    ],
    "count": 3,
    "names": [
      "Sia",
      "Sia",
      "Sia"
    ]
  },
  "43": {
    "status": "ok",
    "faces": [
      {
        "person": "Sia",
        "rolle": "Baby",
        "confidence": 33.8
      },
      {
        "person": "Sia",
        "rolle": "Baby",
        "confidence": 44.8
      },
      {
        "person": "Sia",
        "rolle": "Baby",
        "confidence": 31.7
      }
    ],
    "count": 3,
    "names": [
      "Sia",
      "Sia",
      "Sia"
    ]
  },
  "44": {
    "status": "ok",
    "faces": [
      {
        "person": "Sia",
        "rolle": "Baby",
        "confidence": 30.2
      },
      {
        "person": "Leano",
        "rolle": "Sohn von Vanessa & Mark, Cousin von Sia",
        "confidence": 67.5
      }
    ],
    "count": 2,
    "names": [
      "Sia",
      "Leano"
    ]
  },
  "45": {
    "status": "ok",
    "faces": [
      {
        "person": "Levi",
        "rolle": "Ältester Sohn von Melly & Johannes, Cousin von Sia",
        "confidence": 77.5
      },
      {
        "person": "Sia",
        "rolle": "Baby",
        "confidence": 41.4
      }
    ],
    "count": 2,
    "names": [
      "Levi",
      "Sia"
    ]
  },
  "46": {
    "status": "ok",
    "faces": [
      {
        "person": "Sia",
        "rolle": "Baby",
        "confidence": 25.2
      }
    ],
    "count": 1,
    "names": [
      "Sia"
    ]
  },
  "47": {
    "status": "ok",
    "faces": [
      {
        "person": "Leano",
        "rolle": "Sohn von Vanessa & Mark, Cousin von Sia",
        "confidence": 74.6
      }
    ],
    "count": 1,
    "names": [
      "Leano"
    ]
  },
  "48": {
    "status": "ok",
    "faces": [
      {
        "person": "Sia",
        "rolle": "Baby",
        "confidence": 49.6
      },
      {
        "person": "Tante Melly",
        "rolle": "Tante",
        "confidence": 55.7
      }
    ],
    "count": 2,
    "names": [
      "Sia",
      "Tante Melly"
    ]
  },
  "49": {
    "status": "ok",
    "faces": [
      {
        "person": "Leano",
        "rolle": "Sohn von Vanessa & Mark, Cousin von Sia",
        "confidence": 75.1
      }
    ],
    "count": 1,
    "names": [
      "Leano"
    ]
  },
  "50": {
    "status": "ok",
    "faces": [
      {
        "person": "Sia",
        "rolle": "Baby",
        "confidence": 76.2
      },
      {
        "person": "Sia",
        "rolle": "Baby",
        "confidence": 28.1
      }
    ],
    "count": 2,
    "names": [
      "Sia",
      "Sia"
    ]
  }
}